pytfvars/__init__.py
pytfvars/tfvars.py
pytfvars-1.0.3.dist-info/LICENSE.txt
pytfvars-1.0.3.dist-info/METADATA
pytfvars-1.0.3.dist-info/WHEEL
pytfvars-1.0.3.dist-info/top_level.txt
pytfvars-1.0.3.dist-info/RECORD
