Metadata-Version: 2.1
Name: pytfvars
Version: 1.0.3
Summary: convert python dictionary to tfvars(hcl lang) formatted string
Home-page: https://github.com/hohoonsong/pytfvars
Author: hohoonsong
Author-email: hohoonsong@gmail.com
Project-URL: Bug Tracker, https://github.com/hohoonsong/pytfvars/issues
Classifier: Programming Language :: Python :: 3
Classifier: License :: OSI Approved :: MIT License
Classifier: Operating System :: OS Independent
Requires-Python: >=3.6
License-File: LICENSE.txt
